odoo/addons/l10n_it_fatturapa_out_wt/README.rst
odoo/addons/l10n_it_fatturapa_out_wt/__init__.py
odoo/addons/l10n_it_fatturapa_out_wt/__manifest__.py
odoo/addons/l10n_it_fatturapa_out_wt/i18n/it.po
odoo/addons/l10n_it_fatturapa_out_wt/i18n/l10n_it_fatturapa_out_wt.pot
odoo/addons/l10n_it_fatturapa_out_wt/readme/CONTRIBUTORS.rst
odoo/addons/l10n_it_fatturapa_out_wt/readme/DESCRIPTION.rst
odoo/addons/l10n_it_fatturapa_out_wt/static/description/icon.png
odoo/addons/l10n_it_fatturapa_out_wt/static/description/index.html
odoo/addons/l10n_it_fatturapa_out_wt/tests/__init__.py
odoo/addons/l10n_it_fatturapa_out_wt/tests/test_fatturapa_wt.py
odoo/addons/l10n_it_fatturapa_out_wt/tests/data/IT06363391001_00011.xml
odoo/addons/l10n_it_fatturapa_out_wt/tests/data/IT06363391001_00014.xml
odoo/addons/l10n_it_fatturapa_out_wt/tests/data/IT06363391001_00015.xml
odoo/addons/l10n_it_fatturapa_out_wt/tests/data/IT06363391001_00016.xml
odoo/addons/l10n_it_fatturapa_out_wt/tests/data/IT06363391001_00017.xml
odoo/addons/l10n_it_fatturapa_out_wt/tests/data/IT06363391001_00018.xml
odoo/addons/l10n_it_fatturapa_out_wt/tests/data/IT06363391001_00019.xml
odoo/addons/l10n_it_fatturapa_out_wt/views/account_invoice_it_dati_ritenuta.xml
odoo/addons/l10n_it_fatturapa_out_wt/wizard/__init__.py
odoo/addons/l10n_it_fatturapa_out_wt/wizard/wizard_export_fatturapa.py
odoo14_addon_l10n_it_fatturapa_out_wt-14.0.1.0.1.dist-info/METADATA
odoo14_addon_l10n_it_fatturapa_out_wt-14.0.1.0.1.dist-info/WHEEL
odoo14_addon_l10n_it_fatturapa_out_wt-14.0.1.0.1.dist-info/top_level.txt
odoo14_addon_l10n_it_fatturapa_out_wt-14.0.1.0.1.dist-info/RECORD
