Metadata-Version: 2.1
Name: odoo14-addon-l10n-it-fatturapa-out-wt
Version: 14.0.1.0.1
Summary: Modulo ponte tra emissione fatture elettroniche e ritenute.
Home-page: https://github.com/OCA/l10n-italy
Author: Sergio Corato, Odoo Community Association (OCA)
Author-email: support@odoo-community.org
License: AGPL-3
Platform: UNKNOWN
Classifier: Programming Language :: Python
Classifier: Framework :: Odoo
Classifier: Framework :: Odoo :: 14.0
Classifier: License :: OSI Approved :: GNU Affero General Public License v3
Classifier: Development Status :: 4 - Beta
Requires-Python: >=3.6
Requires-Dist: odoo14-addon-l10n-it-fatturapa
Requires-Dist: odoo14-addon-l10n-it-fatturapa-out
Requires-Dist: odoo14-addon-l10n-it-withholding-tax
Requires-Dist: odoo14-addon-l10n-it-withholding-tax-reason
Requires-Dist: odoo <14.1dev,>=14.0a
